client/__init__.py
client/client.py
client/client/__init__.py
client/client/add_contact.py
client/client/database.py
client/client/del_contact.py
client/client/main_window.py
client/client/main_window_conv.py
client/client/start_dialog.py
client/client/transport.py
client/common/__init__.py
client/common/decos.py
client/common/descryptors.py
client/common/errors.py
client/common/metaclasses.py
client/common/utils.py
client/common/variables.py
client/logs/__init__.py
client/unit_tests/__init__.py
den_chat_server-0.0.1.dist-info/METADATA
den_chat_server-0.0.1.dist-info/WHEEL
den_chat_server-0.0.1.dist-info/top_level.txt
den_chat_server-0.0.1.dist-info/RECORD
