Metadata-Version: 2.1
Name: den-chat-server
Version: 0.0.1
Summary: den_chat_server
Author: Denis Demchenko
Author-email: demchenkodenis1@gmail.com
Requires-Dist: PyQt5
Requires-Dist: sqlalchemy
Requires-Dist: pycryptodome
